{
  "data": [
    {
      "Id": {
        "Value": "pupilid-6ce9e221-6582-4d15-b4fb-ebbe759341c6"
      },
      "Urn": {
        "Value": "123456"
      },
      "ForeName": "Name",
      "LastName": "1"
    },
    {
      "Id": {
        "Value": "pupilid-4ed4622e-8c40-471a-ad56-8abc82d45dc4"
      },
      "Urn": {
        "Value": "123456"
      },
      "ForeName": "Name",
      "LastName": "2"
    },
    {
      "Id": {
        "Value": "pupilid-44f9ae5e-fa34-4e81-b7cf-dddb87c838d9"
      },
      "Urn": {
        "Value": "123456"
      },
      "ForeName": "Name",
      "LastName": "3"
    },
    {
      "Id": {
        "Value": "pupilid-b45caf26-0c37-453b-9571-fa4806c76412"
      },
      "ForeName": "Jazmin",
      "LastName": "Friatt",
      "Urn": {
        "Value": 136028
      }
    },
    {
      "Id": {
        "Value": "pupilid-954e9bf6-2dbb-4892-8063-0ad7b4ab4c34"
      },
      "ForeName": "Amalie",
      "LastName": "Younghusband",
      "Urn": {
        "Value": 136028
      }
    },
    {
      "Id": {
        "Value": "pupilid-d463510f-1e6e-40f0-8816-6c902ce28ff2"
      },
      "ForeName": "Hercules",
      "LastName": "Hillin",
      "Urn": {
        "Value": 136028
      }
    },
    {
      "Id": {
        "Value": "pupilid-038fb554-e5bc-446c-9876-422e22dd74de"
      },
      "ForeName": "Eben",
      "LastName": "Turpie",
      "Urn": {
        "Value": 136028
      }
    },
    {
      "Id": {
        "Value": "pupilid-ee2284fc-ba9e-4168-a391-75ce325436c0"
      },
      "ForeName": "Keri",
      "LastName": "Okroy",
      "Urn": {
        "Value": 136028
      }
    },
    {
      "Id": {
        "Value": "pupilid-500d76c3-8a7d-4185-ac17-e5008e4db46d"
      },
      "ForeName": "Fawnia",
      "LastName": "Acott",
      "Urn": {
        "Value": 136028
      }
    },
    {
      "Id": {
        "Value": "pupilid-569aa246-b332-4a69-8cde-c2f39186fd4b"
      },
      "ForeName": "Jeni",
      "LastName": "Leftwich",
      "Urn": {
        "Value": 136028
      }
    },
    {
      "Id": {
        "Value": "pupilid-90b23b6d-b2b5-4125-b35f-27c8f8f5c2a0"
      },
      "ForeName": "Ulla",
      "LastName": "Sharrem",
      "Urn": {
        "Value": 136028
      }
    },
    {
      "Id": {
        "Value": "pupilid-9281d691-f729-465a-9371-2b0e5a7c5519"
      },
      "ForeName": "Gena",
      "LastName": "Pawelek",
      "Urn": {
        "Value": 136028
      }
    },
    {
      "Id": {
        "Value": "pupilid-c80c4b30-0dc8-4c63-bc73-78dbd08906a6"
      },
      "ForeName": "Sydel",
      "LastName": "Richten",
      "Urn": {
        "Value": 136028
      }
    },
    {
      "Id": {
        "Value": "pupilid-2fe1eff1-ee8b-4490-918d-d00884032281"
      },
      "ForeName": "Kelsey",
      "LastName": "Grishmanov",
      "Urn": {
        "Value": 136028
      }
    },
    {
      "Id": {
        "Value": "pupilid-6d78971e-46b2-4244-b24c-99987ac4d031"
      },
      "ForeName": "Yasmeen",
      "LastName": "Kanwell",
      "Urn": {
        "Value": 136028
      }
    },
    {
      "Id": {
        "Value": "pupilid-9f8cd848-0cd7-4fc3-a214-ca86f010e53b"
      },
      "ForeName": "Tremaine",
      "LastName": "Goodwyn",
      "Urn": {
        "Value": 136028
      }
    },
    {
      "Id": {
        "Value": "pupilid-d31b4d1f-04ec-4d08-bbc0-1ae3660a2467"
      },
      "ForeName": "Jan",
      "LastName": "McCarrell",
      "Urn": {
        "Value": 136028
      }
    },
    {
      "Id": {
        "Value": "pupilid-d54e7e41-3261-4826-a18f-666dc7d9aae4"
      },
      "ForeName": "Petronilla",
      "LastName": "Klimko",
      "Urn": {
        "Value": 136028
      }
    },
    {
      "Id": {
        "Value": "pupilid-f03a0aca-50c3-4ebc-8b86-727fb1d6c11c"
      },
      "ForeName": "Melessa",
      "LastName": "Towndrow",
      "Urn": {
        "Value": 136028
      }
    },
    {
      "Id": {
        "Value": "pupilid-8f9dfb24-1b51-4bfd-ac69-3aba2fba2d56"
      },
      "ForeName": "Pembroke",
      "LastName": "Clohessy",
      "Urn": {
        "Value": 136028
      }
    },
    {
      "Id": {
        "Value": "pupilid-c16af10b-93e7-44c0-98d8-af258b488802"
      },
      "ForeName": "Melva",
      "LastName": "Smallridge",
      "Urn": {
        "Value": 136028
      }
    },
    {
      "Id": {
        "Value": "pupilid-cb3135e4-313e-4124-9448-a7688c7b6965"
      },
      "ForeName": "Lamar",
      "LastName": "Benez",
      "Urn": {
        "Value": 136028
      }
    },
    {
      "Id": {
        "Value": "pupilid-d79ce928-7a31-49f0-bc77-fcab21bebf15"
      },
      "ForeName": "Harlie",
      "LastName": "Beefon",
      "Urn": {
        "Value": 136028
      }
    },
    {
      "Id": {
        "Value": "pupilid-0f00cdd7-6055-49dc-b8f7-c16940c974da"
      },
      "ForeName": "Alexis",
      "LastName": "Duester",
      "Urn": {
        "Value": 136028
      }
    },
    {
      "Id": {
        "Value": "pupilid-d8b3944a-99a0-4bb8-9d72-77277f57308c"
      },
      "ForeName": "Regen",
      "LastName": "Bissex",
      "Urn": {
        "Value": 136028
      }
    },
    {
      "Id": {
        "Value": "pupilid-794c2f13-c95a-412f-b1e5-dbe23f052aba"
      },
      "ForeName": "Judye",
      "LastName": "Asch",
      "Urn": {
        "Value": 136028
      }
    },
    {
      "Id": {
        "Value": "pupilid-a8c53a34-8239-43e6-a3d2-0e0d4115dfd3"
      },
      "ForeName": "Mickie",
      "LastName": "Stalman",
      "Urn": {
        "Value": 136028
      }
    },
    {
      "Id": {
        "Value": "pupilid-d80e815b-24c8-4901-b3bd-12dac5ce4eb3"
      },
      "ForeName": "Diena",
      "LastName": "Asplen",
      "Urn": {
        "Value": 136028
      }
    },
    {
      "Id": {
        "Value": "pupilid-cd012301-b2ac-4855-a4df-5f0c361c955f"
      },
      "ForeName": "Tori",
      "LastName": "Cricket",
      "Urn": {
        "Value": 136028
      }
    },
    {
      "Id": {
        "Value": "pupilid-5ca4cbd7-add1-4208-96f6-1e74e8f5ce9b"
      },
      "ForeName": "Constancia",
      "LastName": "Cristol",
      "Urn": {
        "Value": 136028
      }
    },
    {
      "Id": {
        "Value": "pupilid-9d6c2484-95dd-4789-bc30-44930f0e10d4"
      },
      "ForeName": "Cliff",
      "LastName": "Blackmuir",
      "Urn": {
        "Value": 136028
      }
    },
    {
      "Id": {
        "Value": "pupilid-a9d2e0d4-4751-40d6-9cb4-122d1523ac4b"
      },
      "ForeName": "Isabella",
      "LastName": "Brimblecombe",
      "Urn": {
        "Value": 136028
      }
    },
    {
      "Id": {
        "Value": "pupilid-060a4b65-585a-414e-92d9-ece5d4bc69f6"
      },
      "ForeName": "Bonnee",
      "LastName": "Haythorne",
      "Urn": {
        "Value": 136028
      }
    },
    {
      "Id": {
        "Value": "pupilid-b5e90c29-8951-4149-be40-2e314c4fa53f"
      },
      "ForeName": "Abbot",
      "LastName": "Seers",
      "Urn": {
        "Value": 136028
      }
    },
    {
      "Id": {
        "Value": "pupilid-32f4c756-83ac-4157-9b25-90ed18336a73"
      },
      "ForeName": "Gabbi",
      "LastName": "Danat",
      "Urn": {
        "Value": 136028
      }
    },
    {
      "Id": {
        "Value": "pupilid-c5b75f52-e3ee-4687-b6ea-150929b41aa9"
      },
      "ForeName": "Theressa",
      "LastName": "Thornhill",
      "Urn": {
        "Value": 136028
      }
    },
    {
      "Id": {
        "Value": "pupilid-636ff4c6-c4f1-48ca-80f7-ac599405ae0a"
      },
      "ForeName": "Loretta",
      "LastName": "Haistwell",
      "Urn": {
        "Value": 136028
      }
    },
    {
      "Id": {
        "Value": "pupilid-6a2ef998-8c5a-4cbb-a8ea-45450cdea967"
      },
      "ForeName": "Franni",
      "LastName": "Lusted",
      "Urn": {
        "Value": 136028
      }
    },
    {
      "Id": {
        "Value": "pupilid-ac95fcce-0bd6-4e4c-a37a-e8587fa069c1"
      },
      "ForeName": "Nathan",
      "LastName": "Boddam",
      "Urn": {
        "Value": 136028
      }
    },
    {
      "Id": {
        "Value": "pupilid-88bce853-85ee-49da-9245-224cdc8b80e9"
      },
      "ForeName": "Rocky",
      "LastName": "Strickett",
      "Urn": {
        "Value": 136028
      }
    },
    {
      "Id": {
        "Value": "pupilid-6875efb4-e9b3-439a-8d4f-543da654c765"
      },
      "ForeName": "Jolene",
      "LastName": "Galer",
      "Urn": {
        "Value": 136028
      }
    },
    {
      "Id": {
        "Value": "pupilid-5a40f4c9-3019-4b44-ad36-35f9c5ef53e9"
      },
      "ForeName": "Thornie",
      "LastName": "Waywell",
      "Urn": {
        "Value": 136028
      }
    },
    {
      "Id": {
        "Value": "pupilid-9735a0cf-9240-4f7a-b245-a38100e15f80"
      },
      "ForeName": "Dulcinea",
      "LastName": "McCluin",
      "Urn": {
        "Value": 136028
      }
    },
    {
      "Id": {
        "Value": "pupilid-5680bf32-c48c-4bd1-80f3-ee0739820683"
      },
      "ForeName": "Bernard",
      "LastName": "Metts",
      "Urn": {
        "Value": 136028
      }
    },
    {
      "Id": {
        "Value": "pupilid-54df5e3d-e621-4dfa-9e34-8953d72697f9"
      },
      "ForeName": "Bartlett",
      "LastName": "Gilbertson",
      "Urn": {
        "Value": 136028
      }
    },
    {
      "Id": {
        "Value": "pupilid-6ab9b022-9b80-4a6e-8a68-5cab2f43adab"
      },
      "ForeName": "Hallie",
      "LastName": "Ryding",
      "Urn": {
        "Value": 136028
      }
    },
    {
      "Id": {
        "Value": "pupilid-cab89fb0-4f46-44bb-8b1c-98a712eb8eda"
      },
      "ForeName": "Freida",
      "LastName": "O' Cuolahan",
      "Urn": {
        "Value": 136028
      }
    },
    {
      "Id": {
        "Value": "pupilid-25afceff-67d4-4516-a1cc-1454500f2d9d"
      },
      "ForeName": "Almira",
      "LastName": "Loughead",
      "Urn": {
        "Value": 136028
      }
    },
    {
      "Id": {
        "Value": "pupilid-edd52aae-81c3-48b1-b39d-ff21c072e197"
      },
      "ForeName": "Carma",
      "LastName": "Nosworthy",
      "Urn": {
        "Value": 136028
      }
    },
    {
      "Id": {
        "Value": "pupilid-d99238be-d3f4-458c-be50-5a4396dff813"
      },
      "ForeName": "Clare",
      "LastName": "Ivell",
      "Urn": {
        "Value": 136028
      }
    },
    {
      "Id": {
        "Value": "pupilid-404b4362-9a3f-4f4b-85f4-6a5180a61dc7"
      },
      "ForeName": "Rutger",
      "LastName": "Maciocia",
      "Urn": {
        "Value": 136028
      }
    },
    {
      "Id": {
        "Value": "pupilid-edd06032-0087-460c-97ac-184e454845b7"
      },
      "ForeName": "Orrin",
      "LastName": "Wheelwright",
      "Urn": {
        "Value": 136028
      }
    },
    {
      "Id": {
        "Value": "pupilid-911a5667-f45f-401b-a290-30b519424caa"
      },
      "ForeName": "Amery",
      "LastName": "Petrovic",
      "Urn": {
        "Value": 136028
      }
    },
    {
      "Id": {
        "Value": "pupilid-a7097404-2010-4bac-9fc7-8dddef8335fb"
      },
      "ForeName": "Virgie",
      "LastName": "Tribble",
      "Urn": {
        "Value": 136028
      }
    },
    {
      "Id": {
        "Value": "pupilid-97aa154f-5ad7-4fb8-9a13-5a5087d34a0a"
      },
      "ForeName": "Timofei",
      "LastName": "Icke",
      "Urn": {
        "Value": 136028
      }
    },
    {
      "Id": {
        "Value": "pupilid-bc33288f-8a82-41c6-8f66-97833bef077a"
      },
      "ForeName": "Bay",
      "LastName": "Benford",
      "Urn": {
        "Value": 136028
      }
    },
    {
      "Id": {
        "Value": "pupilid-e06a630e-3147-4c4e-81a2-cf393f401311"
      },
      "ForeName": "Adeline",
      "LastName": "Lochead",
      "Urn": {
        "Value": 136028
      }
    },
    {
      "Id": {
        "Value": "pupilid-4acfcb22-51b9-4375-9476-3df3f25d23cd"
      },
      "ForeName": "Annecorinne",
      "LastName": "Heinzel",
      "Urn": {
        "Value": 136028
      }
    },
    {
      "Id": {
        "Value": "pupilid-50feacd5-963b-4fdd-8847-666565a5fcea"
      },
      "ForeName": "Nolly",
      "LastName": "Igglesden",
      "Urn": {
        "Value": 136028
      }
    },
    {
      "Id": {
        "Value": "pupilid-0d4f03a2-9b6a-4a6c-b824-2dd895aa7722"
      },
      "ForeName": "Clarissa",
      "LastName": "Inett",
      "Urn": {
        "Value": 136028
      }
    },
    {
      "Id": {
        "Value": "pupilid-eec0f045-da05-4296-a4fb-3ef399172100"
      },
      "ForeName": "Myca",
      "LastName": "McAuslene",
      "Urn": {
        "Value": 136028
      }
    },
    {
      "Id": {
        "Value": "pupilid-829de7ea-78bf-451f-b569-32dd7a0048a6"
      },
      "ForeName": "Angelico",
      "LastName": "Braunton",
      "Urn": {
        "Value": 136028
      }
    },
    {
      "Id": {
        "Value": "pupilid-07c646ff-882a-4fcf-acf2-8729172e65a0"
      },
      "ForeName": "Dianna",
      "LastName": "Week",
      "Urn": {
        "Value": 136028
      }
    },
    {
      "Id": {
        "Value": "pupilid-64eb2c0c-c5a1-47e6-8952-dc4ac108b90f"
      },
      "ForeName": "Dian",
      "LastName": "Savoury",
      "Urn": {
        "Value": 136028
      }
    },
    {
      "Id": {
        "Value": "pupilid-3bb34b81-abcd-4fdb-91af-a50dbfa60c07"
      },
      "ForeName": "Miran",
      "LastName": "Cockley",
      "Urn": {
        "Value": 136028
      }
    },
    {
      "Id": {
        "Value": "pupilid-4ce79634-1099-46a4-9a40-a2695656e7c2"
      },
      "ForeName": "Marilyn",
      "LastName": "Matiasek",
      "Urn": {
        "Value": 136028
      }
    },
    {
      "Id": {
        "Value": "pupilid-f4e5d903-2e1c-4b71-ab40-e0748d75058e"
      },
      "ForeName": "Meghann",
      "LastName": "Athey",
      "Urn": {
        "Value": 136028
      }
    },
    {
      "Id": {
        "Value": "pupilid-bed7f3c5-4a7c-474b-9bca-4643bf42a1f1"
      },
      "ForeName": "Lora",
      "LastName": "Weippert",
      "Urn": {
        "Value": 136028
      }
    },
    {
      "Id": {
        "Value": "pupilid-23b70ee8-7c83-4c82-9aec-4bc7729f38eb"
      },
      "ForeName": "Elia",
      "LastName": "Haylock",
      "Urn": {
        "Value": 136028
      }
    },
    {
      "Id": {
        "Value": "pupilid-a6fee483-6e1d-4740-8fa6-740d9a301aeb"
      },
      "ForeName": "Salomone",
      "LastName": "Grinov",
      "Urn": {
        "Value": 136028
      }
    },
    {
      "Id": {
        "Value": "pupilid-741bdac5-9d34-4116-96ad-3186adc42327"
      },
      "ForeName": "Kaspar",
      "LastName": "Mathe",
      "Urn": {
        "Value": 136028
      }
    },
    {
      "Id": {
        "Value": "pupilid-960ea595-6743-4e54-bfa6-8ed82aa654a0"
      },
      "ForeName": "Lainey",
      "LastName": "Gudeman",
      "Urn": {
        "Value": 136028
      }
    },
    {
      "Id": {
        "Value": "pupilid-7ea17b34-b389-4b74-823b-b7bf87757843"
      },
      "ForeName": "Tripp",
      "LastName": "Armiger",
      "Urn": {
        "Value": 136028
      }
    },
    {
      "Id": {
        "Value": "pupilid-8ac96667-5525-4333-b86b-7797a1e9fcac"
      },
      "ForeName": "Berny",
      "LastName": "Earry",
      "Urn": {
        "Value": 136028
      }
    },
    {
      "Id": {
        "Value": "pupilid-a8b2bfe8-9cc7-4220-a9e0-d376058c760b"
      },
      "ForeName": "Lula",
      "LastName": "Firpo",
      "Urn": {
        "Value": 136028
      }
    },
    {
      "Id": {
        "Value": "pupilid-df2183ab-fd45-417b-8996-403ab132cd3e"
      },
      "ForeName": "Viviana",
      "LastName": "Obal",
      "Urn": {
        "Value": 136028
      }
    },
    {
      "Id": {
        "Value": "pupilid-132b2baf-fe13-4a4e-b9ab-b7d7e0095e99"
      },
      "ForeName": "Helaine",
      "LastName": "Labbet",
      "Urn": {
        "Value": 136028
      }
    },
    {
      "Id": {
        "Value": "pupilid-c61791ef-b9e9-45ed-bc59-bc9c6bad1050"
      },
      "ForeName": "Marylin",
      "LastName": "Thornton",
      "Urn": {
        "Value": 136028
      }
    },
    {
      "Id": {
        "Value": "pupilid-1fd0de23-009b-46d4-abcd-c3e6dcc3fc77"
      },
      "ForeName": "Katalin",
      "LastName": "Peete",
      "Urn": {
        "Value": 136028
      }
    },
    {
      "Id": {
        "Value": "pupilid-eaa44499-e6b2-4948-989a-3236b978adab"
      },
      "ForeName": "Monica",
      "LastName": "Abramovitz",
      "Urn": {
        "Value": 136028
      }
    },
    {
      "Id": {
        "Value": "pupilid-163c4b2b-962c-48d3-8324-0b81e82f8ac0"
      },
      "ForeName": "Nessa",
      "LastName": "Klauer",
      "Urn": {
        "Value": 136028
      }
    },
    {
      "Id": {
        "Value": "pupilid-c8418061-648b-47be-81b8-5b1b7ebef9c3"
      },
      "ForeName": "Jemmy",
      "LastName": "Dymond",
      "Urn": {
        "Value": 136028
      }
    },
    {
      "Id": {
        "Value": "pupilid-8f081da8-8c3e-4818-84b2-e95307c7e7a4"
      },
      "ForeName": "Quint",
      "LastName": "Bourne",
      "Urn": {
        "Value": 136028
      }
    },
    {
      "Id": {
        "Value": "pupilid-e215e5a4-d90e-4111-8560-f6df5107490d"
      },
      "ForeName": "Hugh",
      "LastName": "Melling",
      "Urn": {
        "Value": 136028
      }
    },
    {
      "Id": {
        "Value": "pupilid-7e7b1320-7fff-4c9e-8a50-93fbd7042b2e"
      },
      "ForeName": "Cody",
      "LastName": "Caston",
      "Urn": {
        "Value": 136028
      }
    },
    {
      "Id": {
        "Value": "pupilid-3e6821f1-d5c5-4578-8612-9a4984347e1d"
      },
      "ForeName": "Dulcy",
      "LastName": "Guillotin",
      "Urn": {
        "Value": 136028
      }
    },
    {
      "Id": {
        "Value": "pupilid-624e6b2b-5be6-45bd-adb5-57ce551ec8b8"
      },
      "ForeName": "Carolann",
      "LastName": "Wortt",
      "Urn": {
        "Value": 136028
      }
    },
    {
      "Id": {
        "Value": "pupilid-03dc2d06-b777-4844-9d81-41a22b097d1c"
      },
      "ForeName": "Devlen",
      "LastName": "Kellitt",
      "Urn": {
        "Value": 136028
      }
    },
    {
      "Id": {
        "Value": "pupilid-bd591173-837a-4892-a460-85bb25a3e62f"
      },
      "ForeName": "Melodie",
      "LastName": "Polye",
      "Urn": {
        "Value": 136028
      }
    },
    {
      "Id": {
        "Value": "pupilid-e370be20-2f65-4026-b05d-fc7a0cfe6789"
      },
      "ForeName": "Jilleen",
      "LastName": "Naerup",
      "Urn": {
        "Value": 136028
      }
    },
    {
      "Id": {
        "Value": "pupilid-07c9cfe4-e638-49c7-b3f1-605ed420b0ae"
      },
      "ForeName": "Vita",
      "LastName": "Joyson",
      "Urn": {
        "Value": 136028
      }
    },
    {
      "Id": {
        "Value": "pupilid-33527a68-bf7b-4f07-8675-4f322adb115e"
      },
      "ForeName": "Tobi",
      "LastName": "Summersett",
      "Urn": {
        "Value": 136028
      }
    },
    {
      "Id": {
        "Value": "pupilid-09accba1-8127-46e8-bc92-9a709995ef03"
      },
      "ForeName": "Shaylynn",
      "LastName": "Spreag",
      "Urn": {
        "Value": 136028
      }
    },
    {
      "Id": {
        "Value": "pupilid-004167bb-d623-4333-838d-fadfba19d7d3"
      },
      "ForeName": "Andy",
      "LastName": "Leivesley",
      "Urn": {
        "Value": 136028
      }
    },
    {
      "Id": {
        "Value": "pupilid-7661f423-2e8a-4c9a-b903-8be130bcc111"
      },
      "ForeName": "Levey",
      "LastName": "Jirak",
      "Urn": {
        "Value": 136028
      }
    },
    {
      "Id": {
        "Value": "pupilid-c99322ed-cdba-4ae2-b6ab-15d3a70a2c30"
      },
      "ForeName": "Steve",
      "LastName": "McCrachen",
      "Urn": {
        "Value": 136028
      }
    },
    {
      "Id": {
        "Value": "pupilid-42fddbb1-8c81-4d8e-85d7-d42dc3ff9a3a"
      },
      "ForeName": "Westley",
      "LastName": "Gorcke",
      "Urn": {
        "Value": 136028
      }
    },
    {
      "Id": {
        "Value": "pupilid-0efda203-c35f-41e6-a7b6-aaa67afa76c7"
      },
      "ForeName": "Isidoro",
      "LastName": "Giamelli",
      "Urn": {
        "Value": 136028
      }
    },
    {
      "Id": {
        "Value": "pupilid-9d58acae-6e29-4c77-81d6-31bae03a472f"
      },
      "ForeName": "Borden",
      "LastName": "Brundrett",
      "Urn": {
        "Value": 136028
      }
    },
    {
      "Id": {
        "Value": "pupilid-1597e976-65cc-4314-9d1b-1122a78c76d1"
      },
      "ForeName": "Spense",
      "LastName": "O'Glessane",
      "Urn": {
        "Value": 136028
      }
    },
    {
      "Id": {
        "Value": "pupilid-a1a8e369-7d47-420a-930a-0324dc6519db"
      },
      "ForeName": "Tobit",
      "LastName": "Slessar",
      "Urn": {
        "Value": 136028
      }
    },
    {
      "Id": {
        "Value": "pupilid-824de072-d52f-46cc-a865-d91ebe45f6b2"
      },
      "ForeName": "Merrie",
      "LastName": "Camier",
      "Urn": {
        "Value": 136028
      }
    },
    {
      "Id": {
        "Value": "pupilid-ae29b6c1-15b3-40d2-85f6-bdd263e92feb"
      },
      "ForeName": "Melvyn",
      "LastName": "Smeeth",
      "Urn": {
        "Value": 136028
      }
    },
    {
      "Id": {
        "Value": "pupilid-e248a423-7c84-48b8-8f83-ce9aee7f58ae"
      },
      "ForeName": "Lauren",
      "LastName": "Heatly",
      "Urn": {
        "Value": 136028
      }
    },
    {
      "Id": {
        "Value": "pupilid-036fa9bd-568b-45df-a42c-b54ada2ab09b"
      },
      "ForeName": "Rodge",
      "LastName": "Simpole",
      "Urn": {
        "Value": 136028
      }
    },
    {
      "Id": {
        "Value": "pupilid-b1e2dc60-7881-4cbd-a979-9da1f310c0e9"
      },
      "ForeName": "Fionna",
      "LastName": "Postlethwaite",
      "Urn": {
        "Value": 136028
      }
    },
    {
      "Id": {
        "Value": "pupilid-6235f9a8-eca9-49fa-a734-ce8848296138"
      },
      "ForeName": "Berke",
      "LastName": "Uzelli",
      "Urn": {
        "Value": 136028
      }
    },
    {
      "Id": {
        "Value": "pupilid-0a56e6b6-7c61-4820-9e45-aa8b8603439b"
      },
      "ForeName": "Ursuline",
      "LastName": "Askam",
      "Urn": {
        "Value": 136028
      }
    },
    {
      "Id": {
        "Value": "pupilid-ce731549-c18e-47d8-9e82-866509254ed5"
      },
      "ForeName": "Tymothy",
      "LastName": "Lambourne",
      "Urn": {
        "Value": 136028
      }
    },
    {
      "Id": {
        "Value": "pupilid-92ca0fd5-698d-455f-91e0-ccea34ba12fc"
      },
      "ForeName": "Teresita",
      "LastName": "Showen",
      "Urn": {
        "Value": 136028
      }
    },
    {
      "Id": {
        "Value": "pupilid-f4b19055-7d9a-4513-9093-29ba0df1d353"
      },
      "ForeName": "Karissa",
      "LastName": "Hebard",
      "Urn": {
        "Value": 136028
      }
    },
    {
      "Id": {
        "Value": "pupilid-196afe5f-0c48-4e46-b6a0-b0f795159a2e"
      },
      "ForeName": "Wallie",
      "LastName": "Kolakowski",
      "Urn": {
        "Value": 136028
      }
    },
    {
      "Id": {
        "Value": "pupilid-8151b1bf-e655-4ec2-aa21-cd0a730f848f"
      },
      "ForeName": "Lorine",
      "LastName": "Kuhwald",
      "Urn": {
        "Value": 136028
      }
    },
    {
      "Id": {
        "Value": "pupilid-087672af-1800-4486-abf3-f528907e4cae"
      },
      "ForeName": "Baron",
      "LastName": "Danilowicz",
      "Urn": {
        "Value": 136028
      }
    },
    {
      "Id": {
        "Value": "pupilid-4159543c-4b2d-490c-a782-2be6558710bf"
      },
      "ForeName": "Caleb",
      "LastName": "Arblaster",
      "Urn": {
        "Value": 136028
      }
    },
    {
      "Id": {
        "Value": "pupilid-32588bf1-0153-4f0c-b476-07b8681266bc"
      },
      "ForeName": "Davine",
      "LastName": "Goseling",
      "Urn": {
        "Value": 136028
      }
    },
    {
      "Id": {
        "Value": "pupilid-5c95d530-7044-4f3a-8e6d-0fe55509b821"
      },
      "ForeName": "Den",
      "LastName": "Ferier",
      "Urn": {
        "Value": 136028
      }
    },
    {
      "Id": {
        "Value": "pupilid-01a98355-d600-4b87-ae7e-463a7a5d8345"
      },
      "ForeName": "Fritz",
      "LastName": "Minard",
      "Urn": {
        "Value": 136028
      }
    },
    {
      "Id": {
        "Value": "pupilid-68e978f1-a026-4cff-94d7-e3234109d342"
      },
      "ForeName": "Ernestus",
      "LastName": "Stiegers",
      "Urn": {
        "Value": 136028
      }
    },
    {
      "Id": {
        "Value": "pupilid-dd68ac25-09b2-48f5-86fe-d24f3e64631b"
      },
      "ForeName": "Leanna",
      "LastName": "Hilhouse",
      "Urn": {
        "Value": 136028
      }
    },
    {
      "Id": {
        "Value": "pupilid-d1f899be-34e7-4293-8b98-213ab013b6a6"
      },
      "ForeName": "Salvidor",
      "LastName": "Stansby",
      "Urn": {
        "Value": 136028
      }
    },
    {
      "Id": {
        "Value": "pupilid-85343dbc-3f06-4138-a1ce-5f50009f0315"
      },
      "ForeName": "Kippie",
      "LastName": "Goschalk",
      "Urn": {
        "Value": 136028
      }
    },
    {
      "Id": {
        "Value": "pupilid-093e71f3-a80f-4686-8999-0b4893a20bf8"
      },
      "ForeName": "Zerk",
      "LastName": "Imlach",
      "Urn": {
        "Value": 136028
      }
    },
    {
      "Id": {
        "Value": "pupilid-d89c8c9a-8273-4320-90c0-2f9ba98e7d71"
      },
      "ForeName": "Gard",
      "LastName": "McVity",
      "Urn": {
        "Value": 136028
      }
    },
    {
      "Id": {
        "Value": "pupilid-a276cf51-5d7c-4096-b17b-be9c2ae22c0e"
      },
      "ForeName": "Chandra",
      "LastName": "Skains",
      "Urn": {
        "Value": 136028
      }
    },
    {
      "Id": {
        "Value": "pupilid-c4c08a59-9dd6-4d4d-bfd3-5dc3d54f6ed0"
      },
      "ForeName": "Coleen",
      "LastName": "Van den Velden",
      "Urn": {
        "Value": 136028
      }
    },
    {
      "Id": {
        "Value": "pupilid-13ff8bb5-8bfb-4de7-bf87-e4a2184d3bc2"
      },
      "ForeName": "Gregorio",
      "LastName": "Beeck",
      "Urn": {
        "Value": 136028
      }
    },
    {
      "Id": {
        "Value": "pupilid-e79d4f04-e2d2-4ea7-bca6-f93942fd66ac"
      },
      "ForeName": "Kevan",
      "LastName": "Dachs",
      "Urn": {
        "Value": 136028
      }
    },
    {
      "Id": {
        "Value": "pupilid-2bb8694b-52e7-4bb7-a177-0264d1b4d5fc"
      },
      "ForeName": "Amara",
      "LastName": "Adne",
      "Urn": {
        "Value": 136028
      }
    },
    {
      "Id": {
        "Value": "pupilid-c92ffddb-3737-4b4c-92f1-17f7470914f4"
      },
      "ForeName": "Jeannette",
      "LastName": "Brandt",
      "Urn": {
        "Value": 136028
      }
    },
    {
      "Id": {
        "Value": "pupilid-79dbada9-d86b-48b0-9993-0b1b3b425dda"
      },
      "ForeName": "Sharla",
      "LastName": "Skuse",
      "Urn": {
        "Value": 136028
      }
    },
    {
      "Id": {
        "Value": "pupilid-2014eb0b-f96b-4eb3-afc9-00b5fb5ad63b"
      },
      "ForeName": "Jewelle",
      "LastName": "Kinvig",
      "Urn": {
        "Value": 136028
      }
    },
    {
      "Id": {
        "Value": "pupilid-d641a3ed-9644-4e4a-aeff-2f2aad3629ef"
      },
      "ForeName": "Duke",
      "LastName": "MacAlroy",
      "Urn": {
        "Value": 136028
      }
    },
    {
      "Id": {
        "Value": "pupilid-c8ca263c-22af-4cd9-9f02-dd8fc53cafee"
      },
      "ForeName": "Ines",
      "LastName": "Ferschke",
      "Urn": {
        "Value": 136028
      }
    },
    {
      "Id": {
        "Value": "pupilid-e63abd70-99c0-4074-92c0-ddf92861dade"
      },
      "ForeName": "Arleyne",
      "LastName": "Drohan",
      "Urn": {
        "Value": 136028
      }
    },
    {
      "Id": {
        "Value": "pupilid-a79c6cf5-1584-422e-abde-ad631354f7e6"
      },
      "ForeName": "Modestine",
      "LastName": "Skillett",
      "Urn": {
        "Value": 136028
      }
    },
    {
      "Id": {
        "Value": "pupilid-2a2bfd0b-d598-427f-819f-72b21c6ff26f"
      },
      "ForeName": "Lilli",
      "LastName": "Canner",
      "Urn": {
        "Value": 136028
      }
    },
    {
      "Id": {
        "Value": "pupilid-a07f89fd-2bc9-46a2-a5ce-cfc8a78480a3"
      },
      "ForeName": "Brice",
      "LastName": "Lefridge",
      "Urn": {
        "Value": 136028
      }
    },
    {
      "Id": {
        "Value": "pupilid-eeccd4dd-d9fd-4604-b8cb-6cff497fa22c"
      },
      "ForeName": "Tadeo",
      "LastName": "Vasilic",
      "Urn": {
        "Value": 136028
      }
    },
    {
      "Id": {
        "Value": "pupilid-5ae03994-cb3f-4867-a385-66db3e771d2e"
      },
      "ForeName": "Malvin",
      "LastName": "Lumley",
      "Urn": {
        "Value": 136028
      }
    },
    {
      "Id": {
        "Value": "pupilid-427882f1-6e40-46e9-a038-7f1657f926bd"
      },
      "ForeName": "Lesya",
      "LastName": "Labdon",
      "Urn": {
        "Value": 136028
      }
    },
    {
      "Id": {
        "Value": "pupilid-5964dab2-730a-41e6-9d8b-c99e295b51af"
      },
      "ForeName": "Bobby",
      "LastName": "Lang",
      "Urn": {
        "Value": 136028
      }
    },
    {
      "Id": {
        "Value": "pupilid-5b7cb22e-f5fd-4147-b36a-13b34ede8880"
      },
      "ForeName": "Gunilla",
      "LastName": "Abramowsky",
      "Urn": {
        "Value": 136028
      }
    },
    {
      "Id": {
        "Value": "pupilid-d9359ff1-1c46-4b3d-81e0-84774211558b"
      },
      "ForeName": "Therine",
      "LastName": "Brolechan",
      "Urn": {
        "Value": 136028
      }
    },
    {
      "Id": {
        "Value": "pupilid-1db42d71-8f66-4486-86c9-278012debb07"
      },
      "ForeName": "Dylan",
      "LastName": "Delve",
      "Urn": {
        "Value": 136028
      }
    },
    {
      "Id": {
        "Value": "pupilid-572b04db-5ebe-4700-82e9-97285c3d4edb"
      },
      "ForeName": "Otes",
      "LastName": "Hallifax",
      "Urn": {
        "Value": 136028
      }
    },
    {
      "Id": {
        "Value": "pupilid-3617c0f4-5ee8-44c5-97d9-0d5dcaf1e18d"
      },
      "ForeName": "Julee",
      "LastName": "Colby",
      "Urn": {
        "Value": 136028
      }
    },
    {
      "Id": {
        "Value": "pupilid-37c2907a-dbef-4784-ba86-bf804fdf47b8"
      },
      "ForeName": "Johnny",
      "LastName": "O'Tuohy",
      "Urn": {
        "Value": 136028
      }
    },
    {
      "Id": {
        "Value": "pupilid-67cbf71f-8b82-4b97-bc5d-5a5c9bda9516"
      },
      "ForeName": "Felizio",
      "LastName": "Veall",
      "Urn": {
        "Value": 136028
      }
    },
    {
      "Id": {
        "Value": "pupilid-06b136d4-878f-4227-bdde-d6eff190985f"
      },
      "ForeName": "Reinhard",
      "LastName": "Resdale",
      "Urn": {
        "Value": 136028
      }
    },
    {
      "Id": {
        "Value": "pupilid-e33a598f-219f-4c62-afa7-b3343face186"
      },
      "ForeName": "Colline",
      "LastName": "Sattin",
      "Urn": {
        "Value": 136028
      }
    },
    {
      "Id": {
        "Value": "pupilid-50b30016-cde1-412d-a777-90bda0ccb264"
      },
      "ForeName": "Vonny",
      "LastName": "Freeberne",
      "Urn": {
        "Value": 136028
      }
    },
    {
      "Id": {
        "Value": "pupilid-a94ad363-4b96-42b7-ba24-e4c8bc9401e9"
      },
      "ForeName": "Merrill",
      "LastName": "Halm",
      "Urn": {
        "Value": 136028
      }
    }
  ]
}